serverless_config/__init__.py
serverless_config/composite_config.py
serverless_config/config_base.py
serverless_config/env_config.py
serverless_config/ssm_config.py
serverless_config-0.1.5.dev4.dist-info/DESCRIPTION.rst
serverless_config-0.1.5.dev4.dist-info/METADATA
serverless_config-0.1.5.dev4.dist-info/RECORD
serverless_config-0.1.5.dev4.dist-info/WHEEL
serverless_config-0.1.5.dev4.dist-info/metadata.json
serverless_config-0.1.5.dev4.dist-info/top_level.txt
